psynova/__init__.py
psynova/__main__.py
psynova/client.py
psynova/exceptions.py
psynova/version.txt
psynova-1.4.dist-info/LICENSE
psynova-1.4.dist-info/METADATA
psynova-1.4.dist-info/WHEEL
psynova-1.4.dist-info/entry_points.txt
psynova-1.4.dist-info/top_level.txt
psynova-1.4.dist-info/RECORD
