Metadata-Version: 2.2
Name: psynova
Version: 1.4
Summary: A powerful and flexible AI agent framework in Python
Home-page: https://psynova.github.io/
Author: psynova-dev
Author-email: dev@psynova.ai
Keywords: ai,agent,framework,machine learning,artificial intelligence
Requires-Python: >=3.10
License-File: LICENSE
Requires-Dist: requests==2.31.0
Requires-Dist: rich==13.9.4
Dynamic: author
Dynamic: author-email
Dynamic: description
Dynamic: description-content-type
Dynamic: home-page
Dynamic: keywords
Dynamic: requires-dist
Dynamic: requires-python
Dynamic: summary
